lapdog/__init__.py
lapdog/__main__.py
lapdog/adapters.py
lapdog/auth.py
lapdog/cache.py
lapdog/gateway.py
lapdog/lapdog.py
lapdog/api/__init__.py
lapdog/api/__main__.py
lapdog/api/controllers.py
lapdog/api/swagger/lapdog.yaml
lapdog/cloud/__init__.py
lapdog/cloud/abort.py
lapdog/cloud/auth.py
lapdog/cloud/internal.py
lapdog/cloud/patch.py
lapdog/cloud/query.py
lapdog/cloud/quotas.py
lapdog/cloud/register.py
lapdog/cloud/resolution.py
lapdog/cloud/submit.py
lapdog/cloud/utils.py
lapdog/cloud/webhook.py
lapdog/cromwell/LICENSE
lapdog/cromwell/README.md
lapdog/cromwell/wdl_pipeline.yaml
lapdog/vue/.babelrc
lapdog/vue/index.html
lapdog/vue/package.json
lapdog/vue/webpack.config.js
lapdog/vue/src/App.vue
lapdog/vue/src/main.js
lapdog/vue/src/Components/Pagination.vue
lapdog/vue/src/Components/Preview.vue
lapdog/vue/src/Pages/Home.vue
lapdog/vue/src/Pages/Methods.vue
lapdog/vue/src/Pages/Submission.vue
lapdog/vue/src/Pages/Workspace.vue
lapdog-0.18.10.dist-info/LICENSE
lapdog-0.18.10.dist-info/METADATA
lapdog-0.18.10.dist-info/WHEEL
lapdog-0.18.10.dist-info/entry_points.txt
lapdog-0.18.10.dist-info/top_level.txt
lapdog-0.18.10.dist-info/RECORD
