Metadata-Version: 2.1
Name: lapdog
Version: 0.18.10
Summary: A relaxed wrapper for FISS and dalmatian
Home-page: https://github.com/broadinstitute/lapdog
Author: Aaron Graubert - Broad Institute - Cancer Genome Computational Analysis
Author-email: aarong@broadinstitute.org
License: MIT
Platform: UNKNOWN
Classifier: Development Status :: 4 - Beta
Classifier: Programming Language :: Python :: 3
Classifier: Intended Audience :: Science/Research
Classifier: Topic :: Scientific/Engineering :: Bio-Informatics
Classifier: Topic :: System :: Clustering
Classifier: Topic :: System :: Distributed Computing
Classifier: License :: OSI Approved :: MIT License
Requires-Dist: firecloud (>=0.16.9)
Requires-Dist: firecloud-dalmatian (>=0.0.17)
Requires-Dist: hound (>=0.2.0)
Requires-Dist: google-cloud-storage (>=1.23.0)
Requires-Dist: google-cloud-logging (>=1.13.0)
Requires-Dist: googleapis-common-protos (>=1.6.0)
Requires-Dist: google-cloud-core (>=1.1.0)
Requires-Dist: google-auth (>=1.8.2)
Requires-Dist: google-cloud-kms (>=1.2.1)
Requires-Dist: google-api-core[grpc] (>=1.14.2)
Requires-Dist: PyYAML (>=5.1)
Requires-Dist: agutil (>=4.0.2)
Requires-Dist: Flask-Cors (>=3.0.7)
Requires-Dist: crayons (>=0.2.0)
Requires-Dist: connexion (>=2.2.0)
Requires-Dist: oauth2client (>=4.1.3)
Requires-Dist: requests (>=2.22.0)
Requires-Dist: cryptography (>=2.3.0)
Requires-Dist: pyOpenSSL (>=19.0.0)
Requires-Dist: protobuf (>=3.6.0)
Requires-Dist: iso8601 (>=0.1.12)
Requires-Dist: pandas (>=0.20.0)
